scanpy_cli/__init__.py
scanpy_cli/io/__init__.py
scanpy_cli/io/read_10x_h5.py
scanpy_cli/pl/__init__.py
scanpy_cli/pl/umap.py
scanpy_cli/pp/__init__.py
scanpy_cli/pp/bbknn.py
scanpy_cli/pp/combat.py
scanpy_cli/pp/filter_cells.py
scanpy_cli/pp/filter_genes.py
scanpy_cli/pp/harmony.py
scanpy_cli/pp/highly_variable_genes.py
scanpy_cli/pp/neighbors.py
scanpy_cli/pp/pca.py
scanpy_cli/pp/regress_out.py
scanpy_cli/pp/scanorama.py
scanpy_cli/pp/scrublet.py
scanpy_cli/tl/__init__.py
scanpy_cli/tl/leiden.py
scanpy_cli/tl/paga.py
scanpy_cli/tl/rank_genes_groups.py
scanpy_cli/tl/umap.py
scanpy_cli-0.2.0.dist-info/METADATA
scanpy_cli-0.2.0.dist-info/WHEEL
scanpy_cli-0.2.0.dist-info/entry_points.txt
scanpy_cli-0.2.0.dist-info/RECORD
