Metadata-Version: 2.4
Name: scanpy-cli
Version: 0.2.0
Summary: CLI for the scanpy package
Author-email: nictru <nictru32@gmail.com>
Classifier: License :: OSI Approved :: MIT License
Classifier: Operating System :: OS Independent
Classifier: Programming Language :: Python :: 3
Requires-Python: >=3.12
Requires-Dist: bbknn>=1.6.0
Requires-Dist: harmonypy>=0.0.10
Requires-Dist: igraph>=0.11.8
Requires-Dist: leidenalg>=0.10.2
Requires-Dist: rich-click>=1.8.8
Requires-Dist: scanorama>=1.7.4
Requires-Dist: scanpy>=1.11.0
Requires-Dist: scikit-image>=0.25.2
Provides-Extra: testing
Requires-Dist: pytest-cov>=5.0.0; extra == 'testing'
Requires-Dist: pytest>=8.3.5; extra == 'testing'
